{
  "version": "v3.3.2-mermaid-quality-brain-v2.2",
  "system_codename": "Mermaid",
  "assistant_operator": "BB",
  "mission": "Classify story type correctly, enforce sport floors, and keep HSD queues editorially useful.",
  "min_quality_score": 50,
  "sport_floors": {
    "WNBA": 4,
    "NWSL": 2,
    "WTA": 2,
    "LPGA": 1,
    "Volleyball": 1,
    "USWNT": 1,
    "NCAA Softball": 1
  },
  "league_caps": {
    "WNBA": 8,
    "NWSL": 5,
    "WTA": 5,
    "LPGA": 4,
    "Volleyball": 4,
    "VNL": 4,
    "USWNT": 4,
    "FIFA Women": 4,
    "NCAA Softball": 4
  },
  "junk_exact_titles": [
    "skip to main content",
    "go back to the home page",
    "home",
    "privacy policy",
    "terms of use",
    "cookie policy",
    "contact us",
    "about",
    "about the wta",
    "partnerships",
    "leadership team",
    "player listing",
    "head-to-head",
    "where to watch",
    "how to watch",
    "inside the game",
    "player stats",
    "add to calendar",
    "previous seasons",
    "free agency hub",
    "standings",
    "stats"
  ],
  "junk_contains": [
    "privacy",
    "cookie",
    "terms",
    "accessibility",
    "newsletter",
    "tickets",
    "shop",
    "store",
    "sponsors",
    "advertising",
    "careers",
    "login",
    "sign in",
    "watch live",
    "league leaders"
  ],
  "team_homepage_titles": [
    "Atlanta Dream",
    "Chicago Sky",
    "Connecticut Sun",
    "Dallas Wings",
    "Golden State Valkyries",
    "Indiana Fever",
    "Las Vegas Aces",
    "Los Angeles Sparks",
    "Minnesota Lynx",
    "New York Liberty",
    "Phoenix Mercury",
    "Portland Fire",
    "Seattle Storm",
    "Toronto Tempo",
    "Washington Mystics"
  ],
  "story_signal_keywords": [
    "announces",
    "named",
    "signs",
    "returns",
    "injury",
    "availability",
    "roster",
    "trade",
    "transfer",
    "wins",
    "defeats",
    "beats",
    "tops",
    "clinches",
    "sets",
    "record",
    "preview",
    "schedule",
    "draw",
    "final",
    "semifinal",
    "quarterfinal",
    "championship",
    "tournament",
    "open",
    "cup",
    "call-up",
    "called up",
    "international",
    "break",
    "rankings",
    "matchup"
  ],
  "source_balancing": {
    "supplemental_fetch_enabled": true,
    "max_links_per_source": 10,
    "timeout_seconds": 12
  }
}
